fastybird_shelly_connector/__init__.py
fastybird_shelly_connector/bootstrap.py
fastybird_shelly_connector/connector.py
fastybird_shelly_connector/entities.py
fastybird_shelly_connector/exceptions.py
fastybird_shelly_connector/logger.py
fastybird_shelly_connector/py.typed
fastybird_shelly_connector/types.py
fastybird_shelly_connector/api/__init__.py
fastybird_shelly_connector/api/gen1_coap_description.json
fastybird_shelly_connector/api/gen1_coap_status.json
fastybird_shelly_connector/api/gen1_http_description.json
fastybird_shelly_connector/api/gen1_http_settings.json
fastybird_shelly_connector/api/gen1_http_shelly.json
fastybird_shelly_connector/api/gen1_http_status.json
fastybird_shelly_connector/api/gen1parser.py
fastybird_shelly_connector/api/gen1validator.py
fastybird_shelly_connector/api/transformers.py
fastybird_shelly_connector/clients/__init__.py
fastybird_shelly_connector/clients/client.py
fastybird_shelly_connector/clients/coap.py
fastybird_shelly_connector/clients/http.py
fastybird_shelly_connector/clients/mdns.py
fastybird_shelly_connector/consumers/__init__.py
fastybird_shelly_connector/consumers/consumer.py
fastybird_shelly_connector/consumers/device.py
fastybird_shelly_connector/consumers/entities.py
fastybird_shelly_connector/events/__init__.py
fastybird_shelly_connector/events/events.py
fastybird_shelly_connector/events/listeners.py
fastybird_shelly_connector/registry/__init__.py
fastybird_shelly_connector/registry/model.py
fastybird_shelly_connector/registry/records.py
fastybird_shelly_connector/utilities/__init__.py
fastybird_shelly_connector/utilities/helpers.py
tests/__init__.py
tests/pytests/__init__.py
tests/pytests/utilities/__init__.py
tests/pytests/utilities/test_transformers.py
fastybird_shelly_connector-0.36.0.dist-info/LICENSE.md
fastybird_shelly_connector-0.36.0.dist-info/METADATA
fastybird_shelly_connector-0.36.0.dist-info/WHEEL
fastybird_shelly_connector-0.36.0.dist-info/top_level.txt
fastybird_shelly_connector-0.36.0.dist-info/RECORD
